{
   "endingTime": "2019-10",
   "input": "index_monthly.txt",
   "description": "Number of platforms in the DU per PU per momt (over the last year)",
   "id": "kpi2f",
   "startingTime": "2018-11",
   "product": "INSITU_BAL_NRT_OBSERVATIONS_013_032",
   "moreInfo": "Monitors the number of platforms in the DU per PU per month during last year, comparing it with the maximum in the period as a reference",
   "dataset": "bal_multiparameter_nrt",
   "plotLines": [
      {
         "label": {
            "text": "17 ref(max)",
            "style": {
               "color": "#F03A47",
               "fontSize": "9px"
            },
            "align": "right"
         },
         "color": "#F03A47",
         "dashStyle": "shortdash",
         "value": 17,
         "width": 1
      },
      {},
      {},
      {},
      {},
      {
         "label": {
            "text": "188 ref(max)",
            "style": {
               "color": "#AB47BC",
               "fontSize": "9px"
            },
            "align": "right"
         },
         "color": "#AB47BC",
         "dashStyle": "shortdash",
         "value": 188,
         "width": 1
      },
      {}
   ],
   "period": "monthly",
   "unit": "platform",
   "shortName": "Number of platforms (over the last year)",
   "series": [
      {
         "color": "#F03A47",
         "data": [
            [
               1541030400000.0,
               16
            ],
            [
               1543622400000.0,
               14
            ],
            [
               1546300800000.0,
               14
            ],
            [
               1548979200000.0,
               12
            ],
            [
               1551398400000.0,
               13
            ],
            [
               1554076800000.0,
               12
            ],
            [
               1556668800000.0,
               15
            ],
            [
               1559347200000.0,
               15
            ],
            [
               1561939200000.0,
               17
            ],
            [
               1564617600000.0,
               16
            ],
            [
               1567296000000.0,
               16
            ],
            [
               1569888000000.0,
               13
            ]
         ],
         "name": "GL"
      },
      {
         "color": "#347FC4",
         "data": [],
         "name": "IR"
      },
      {
         "color": "#399B60",
         "data": [],
         "name": "MO"
      },
      {
         "color": "#26C6DA",
         "data": [],
         "name": "AR"
      },
      {
         "color": "#F9A825",
         "data": [],
         "name": "NO"
      },
      {
         "color": "#AB47BC",
         "data": [
            [
               1541030400000.0,
               180
            ],
            [
               1543622400000.0,
               175
            ],
            [
               1546300800000.0,
               179
            ],
            [
               1548979200000.0,
               175
            ],
            [
               1551398400000.0,
               180
            ],
            [
               1554076800000.0,
               183
            ],
            [
               1556668800000.0,
               183
            ],
            [
               1559347200000.0,
               181
            ],
            [
               1561939200000.0,
               179
            ],
            [
               1564617600000.0,
               187
            ],
            [
               1567296000000.0,
               188
            ],
            [
               1569888000000.0,
               186
            ]
         ],
         "name": "BO"
      },
      {
         "color": "#EF9A9A",
         "data": [],
         "name": "BS"
      }
   ]
}